isovec/__init__.py
isovec/constants.py
isovec/conversion.py
isovec/element.py
isovec/elements.py
isovec/isotope.py
isovec/isotopes.py
isovec/mixture.py
isovec/molecule.py
isovec/node.py
isovec/substance.py
isovec-1.2.2.dist-info/LICENSE
isovec-1.2.2.dist-info/METADATA
isovec-1.2.2.dist-info/WHEEL
isovec-1.2.2.dist-info/top_level.txt
isovec-1.2.2.dist-info/RECORD
