Metadata-Version: 2.1
Name: isovec
Version: 1.2.2
Summary: A package to calculate atomic, weight or volume composition of (custom) elements, molecules and mixtures, down to isotopic composition.
Author-email: Julius Mercz <julius.mercz@tum.de>
License: MIT License
Project-URL: PyPI, https://pypi.org/project/isovec/
Project-URL: GitHub, https://github.com/jmercz/isoVec
Keywords: isotope,element,molecule,mixture,alloy,material,composition,weight,atomic,mole,volume
Classifier: Development Status :: 5 - Production/Stable
Classifier: Topic :: Scientific/Engineering :: Physics
Classifier: Intended Audience :: Science/Research
Classifier: License :: OSI Approved :: MIT License
Classifier: Programming Language :: Python :: 3
Classifier: Operating System :: OS Independent
Classifier: Typing :: Typed
Requires-Python: >=3.10
License-File: LICENSE
